{
    "session_id": "b9799d41-93a6-4b6f-a4ae-07360c41a382",
    "generated_at": "2026-03-19 18:09:37",
    "summary": {
        "documents": {
            "old": "C:\\Users\\Lenovo\\.vscode\\Python\\yourise.ai\\backend\\tmp_uploads\\old_test.docx",
            "new": "C:\\Users\\Lenovo\\.vscode\\Python\\yourise.ai\\backend\\tmp_uploads\\new_test.docx"
        },
        "stats": {
            "total_changes": 13,
            "red": 2,
            "yellow": 5,
            "green": 6
        }
    },
    "changes_by_risk": {
        "red": [
            {
                "change_id": "3b3af4ba-3d0b-4550-8b95-4ff7b1561d99",
                "number": "5.1",
                "type": "modified",
                "old_text": "",
                "new_text": "За разглашение коммерческой тайны работник обязан возместить упущенную выгоду Общества.  [← НАРУШЕНИЕ! Закон №16-З, ст.19 не требует возмещения упущенной выгоды, только убытки]",
                "issue": {
                    "explanation": "В добавленном тексте установлено обязательство работника возместить упущенную выгоду, тогда как закон №16-З, ст.19 (и ст.18) предусматривает возмещение только убытков, а не упущенной выгоды. Таким образом, требование противоречит норме закона.",
                    "law_reference": "C:\\Users\\Lenovo\\Downloads\\H11300016_1357765200, ст.18",
                    "suggestion": "Заменить формулировку «возместить упущенную выгоду» на «возместить убытки», либо полностью убрать требование о возмещении упущенной выгоды.",
                    "advice": "Критическая ошибка. Требуется исправление."
                }
            },
            {
                "change_id": "97f42bb0-43ab-48ab-a1d8-997cfbdde28e",
                "number": "6",
                "type": "modified",
                "old_text": "",
                "new_text": "Внесение изменений",
                "issue": {
                    "explanation": "Закон требует, чтобы в тексте присутствовали как \"внесение изменений\", так и \"дополнений в кодексы\". Добавленный фрагмент содержит только \"Внесение изменений\" и не включает требуемую часть о дополнениях, что нарушает требование статьи.",
                    "law_reference": "H11300016_1357765200, ст.21",
                    "suggestion": "Дополнить текст до полного соответствия закону, например: \"Внесение изменений и дополнений в кодексы\".",
                    "advice": "Критическая ошибка. Требуется исправление."
                }
            }
        ],
        "yellow": [
            {
                "change_id": "856c88c4-50e9-4b70-a2d5-8b150cd9b656",
                "number": "—",
                "type": "modified",
                "old_text": "от 15.01.2025 № 5",
                "new_text": "от 20.03.2026 № 12",
                "issue": {
                    "explanation": "Изменение даты и номера документа не затрагивает условия правовой охраны секрета производства, указанные в ст. 1010. Статья регулирует требования к содержанию, хранению и использованию ноу-хау, а не формальные реквизиты ссылок на документы.",
                    "law_reference": "H11300016_1357765200, ст.1010",
                    "suggestion": "Изменение корректно; дополнительных правок не требуется.",
                    "advice": "Внимание. Потенциальный риск, требуется проверка юристом."
                }
            },
            {
                "change_id": "c81e100d-4fe5-4506-b358-a0c52e48073d",
                "number": "2.1",
                "type": "modified",
                "old_text": "К коммерческой тайне Общества относятся: - сведения о финансовом состоянии; - сведения о клиентах и поставщиках; - сведения о разрабатываемых технологиях.",
                "new_text": "К коммерческой тайне Общества относятся: - сведения о финансовом состоянии; - сведения о клиентах и поставщиках; - сведения о задолженности по выплате заработной платы - сведения о нарушениях трудовой дисциплины",
                "issue": {
                    "explanation": "Статья 1 (часть 2) лишь определяет, что сведения, составляющие коммерческую тайну, должны быть защищены от раскрытия без согласия владельца. В ней не ограничивает перечень сведений, которые могут считаться коммерческой тайной, поэтому добавление сведений о задолженности по выплате заработной платы и о нарушениях трудовой дисциплины не противоречит данному пункту закона. Возможные конфликты могут возникнуть с другими нормативными актами (например, законом о персональных данных), но в рамках представленной статьи прямого или косвенного противоречия нет.",
                    "law_reference": "H11300016_1357765200, ст.1 (часть 2)",
                    "suggestion": "При включении в перечень коммерческой тайны сведений, относящихся к персональным данным работников, необходимо обеспечить их защиту в соответствии с законом о персональных данных и получить согласие субъектов данных, если это требуется.",
                    "advice": "Внимание. Потенциальный риск, требуется проверка юристом."
                }
            },
            {
                "change_id": "b7a5c3bb-2c22-4f35-b377-e3f2a30674d2",
                "number": "4.1",
                "type": "modified",
                "old_text": "Доступ к сведениям, составляющим коммерческую тайну, предоставляется работникам в соответствии с их должностными обязанностями.",
                "new_text": "Доступ к сведениям, составляющим коммерческую тайну, предоставляется только работникам, имеющим допуск к государственной тайне.",
                "issue": {
                    "explanation": "Статья 11 часть 2 закона защищает право на законный доступ к сведениям, составляющим коммерческую тайну, и предусматривает ответственность за препятствование такому доступу. Ограничение доступа только работникам, имеющим допуск к государственной тайне, создает дополнительный барьер, не предусмотренный законом, и тем самым препятствует законному доступу, что противоречит принципу, закрепленному в статье.",
                    "law_reference": "H11300016_1357765200, ст.11 (часть 2)",
                    "suggestion": "Установить доступ к сведениям, составляющим коммерческую тайну, на основании должностных обязанностей работников, а не только наличия допуска к государственной тайне.",
                    "advice": "Внимание. Потенциальный риск, требуется проверка юристом."
                }
            },
            {
                "change_id": "bde6a379-e369-4da2-83c5-978dbb2abb51",
                "number": "4.2",
                "type": "modified",
                "old_text": "",
                "new_text": "Решение о допуске принимает служба безопасности единолично.",
                "issue": {
                    "explanation": "Текст статьи 11 части 2 регулирует ответственность за препятствия в получении доступа к сведениям, составляющим коммерческую тайну. Добавленное предложение о том, что решение о допуске принимает служба безопасности единолично, не противоречит требованиям этой статьи и не затрагивает регулируемые ею вопросы.",
                    "law_reference": "H11300016_1357765200, ст.11 (часть 2)",
                    "suggestion": "Изменение не требует корректировки с точки зрения указанной статьи закона.",
                    "advice": "Внимание. Потенциальный риск, требуется проверка юристом."
                }
            },
            {
                "change_id": "400b04f6-d5d4-41fa-bcf1-1d424104d922",
                "number": "5",
                "type": "modified",
                "old_text": "",
                "new_text": "Ответственность за нарушение",
                "issue": {
                    "explanation": "Статья 21 регламентирует порядок внесения изменений и дополнений в кодексы, требуя конкретного содержания и правового обоснования. Добавленный элемент представляет собой лишь заголовок «Ответственность за нарушение» без дальнейшего текста, что не соответствует требованиям статьи о полном и обоснованном изложении изменений.",
                    "law_reference": "H11300016_1357765200, ст.21",
                    "suggestion": "Разработать и включить в элемент полный текст, определяющий виды ответственности, размеры штрафов, порядок привлечения к ответственности и правовые основания, чтобы соответствовать требованиям статьи 21.",
                    "advice": "Внимание. Потенциальный риск, требуется проверка юристом."
                }
            }
        ],
        "green": [
            {
                "change_id": null,
                "number": "—",
                "type": "deleted",
                "old_text": "За разглашение коммерческой тайны работники могут быть привлечены к дисциплинарной ответственности.",
                "new_text": "",
                "issue": {
                    "explanation": "Плановое изменение",
                    "law_reference": "Не требуется",
                    "suggestion": "",
                    "advice": "Допустимо. Соответствует законодательству."
                }
            },
            {
                "change_id": null,
                "number": "—",
                "type": "deleted",
                "old_text": "Допуск работников осуществляется на основании приказа директора.",
                "new_text": "",
                "issue": {
                    "explanation": "Плановое изменение",
                    "law_reference": "Не требуется",
                    "suggestion": "",
                    "advice": "Допустимо. Соответствует законодательству."
                }
            },
            {
                "change_id": null,
                "number": "—",
                "type": "deleted",
                "old_text": "Заключительные положения",
                "new_text": "",
                "issue": {
                    "explanation": "Плановое изменение",
                    "law_reference": "Не требуется",
                    "suggestion": "",
                    "advice": "Допустимо. Соответствует законодательству."
                }
            },
            {
                "change_id": null,
                "number": "—",
                "type": "moved",
                "old_text": "",
                "new_text": "",
                "issue": {
                    "explanation": "Плановое изменение",
                    "law_reference": "Не требуется",
                    "suggestion": "",
                    "advice": "Допустимо. Соответствует законодательству."
                }
            },
            {
                "change_id": null,
                "number": "—",
                "type": "moved",
                "old_text": "",
                "new_text": "",
                "issue": {
                    "explanation": "Плановое изменение",
                    "law_reference": "Не требуется",
                    "suggestion": "",
                    "advice": "Допустимо. Соответствует законодательству."
                }
            },
            {
                "change_id": "aac7cd7e-2928-417b-b72b-a7dee18b328e",
                "number": "3.2",
                "type": "modified",
                "old_text": "",
                "new_text": "Работники обязаны подписать обязательство о неразглашении коммерческой тайны в течение 3 дней с даты ознакомления с Положением.",
                "issue": {
                    "explanation": "Статья 16 закона обязывает работников подписать обязательство о неразглашении коммерческой тайны по требованию нанимателя, но не устанавливает конкретный срок. Добавление внутреннего требования подписать обязательство в течение 3 дней не противоречит закону, а лишь уточняет порядок исполнения обязательства.",
                    "law_reference": "C:\\Users\\Lenovo\\Downloads\\H11300016_1357765200, ст.16",
                    "suggestion": "Сохранить требование о подписании в течение 3 дней, так как оно не нарушает закон, но при желании можно уточнить, что срок является внутренним регламентом работодателя.",
                    "advice": "Допустимо. Соответствует законодательству."
                }
            }
        ]
    },
    "download_links": {
        "json": "/api/reports/b9799d41-93a6-4b6f-a4ae-07360c41a382/json",
        "docx": "/api/reports/b9799d41-93a6-4b6f-a4ae-07360c41a382/docx"
    }
}